disentanglement_datasets/__init__.py
disentanglement_datasets/base.py
disentanglement_datasets/dsprites.py
disentanglement_datasets/mpi3d.py
disentanglement_datasets/resource.py
pytorch_disentanglement_datasets-0.0.1.dist-info/LICENSE
pytorch_disentanglement_datasets-0.0.1.dist-info/METADATA
pytorch_disentanglement_datasets-0.0.1.dist-info/WHEEL
pytorch_disentanglement_datasets-0.0.1.dist-info/top_level.txt
pytorch_disentanglement_datasets-0.0.1.dist-info/RECORD
