Metadata-Version: 2.1
Name: pytorch-disentanglement-datasets
Version: 0.0.1
Summary: PyTorch datasets with a focus on disentanglement
Author-email: Walter Nelson <walterj.nelson@mail.utoronto.ca>
License: MIT License        
Project-URL: Homepage, https://github.com/wjn0/pytorch-disentanglement-datasets
Project-URL: Bug Tracker, https://github.com/wjn0/pytorch-disentanglement-datasets/issues
Classifier: Programming Language :: Python :: 3
Classifier: License :: OSI Approved :: MIT License
Classifier: Operating System :: OS Independent
Requires-Python: >=3.7
License-File: LICENSE
Requires-Dist: numpy
Requires-Dist: torch
Requires-Dist: torchvision
